odoo/addons/ssi_partner_company_capital/README.rst
odoo/addons/ssi_partner_company_capital/__init__.py
odoo/addons/ssi_partner_company_capital/__manifest__.py
odoo/addons/ssi_partner_company_capital/models/__init__.py
odoo/addons/ssi_partner_company_capital/models/company_shareholder.py
odoo/addons/ssi_partner_company_capital/models/res_partner.py
odoo/addons/ssi_partner_company_capital/security/ir.model.access.csv
odoo/addons/ssi_partner_company_capital/static/description/icon.png
odoo/addons/ssi_partner_company_capital/views/res_partner_views.xml
odoo14_addon_ssi_partner_company_capital-14.0.1.1.0.dist-info/METADATA
odoo14_addon_ssi_partner_company_capital-14.0.1.1.0.dist-info/WHEEL
odoo14_addon_ssi_partner_company_capital-14.0.1.1.0.dist-info/top_level.txt
odoo14_addon_ssi_partner_company_capital-14.0.1.1.0.dist-info/RECORD
